rackio_swagger/__init__.py
rackio_swagger/_singleton.py
rackio_swagger/core.py
rackio_swagger/schema.py
rackio_swagger/spec.py
rackio_swagger/falcon_swagger_ui/__init__.py
rackio_swagger/falcon_swagger_ui/resources.py
rackio_swagger/falcon_swagger_ui/dist/favicon-16x16.png
rackio_swagger/falcon_swagger_ui/dist/favicon-32x32.png
rackio_swagger/falcon_swagger_ui/dist/index.html
rackio_swagger/falcon_swagger_ui/dist/oauth2-redirect.html
rackio_swagger/falcon_swagger_ui/dist/swagger-ui-bundle.js
rackio_swagger/falcon_swagger_ui/dist/swagger-ui-bundle.js.map
rackio_swagger/falcon_swagger_ui/dist/swagger-ui-standalone-preset.js
rackio_swagger/falcon_swagger_ui/dist/swagger-ui-standalone-preset.js.map
rackio_swagger/falcon_swagger_ui/dist/swagger-ui.css
rackio_swagger/falcon_swagger_ui/dist/swagger-ui.css.map
rackio_swagger/falcon_swagger_ui/dist/swagger-ui.js
rackio_swagger/falcon_swagger_ui/dist/swagger-ui.js.map
rackio_swagger/falcon_swagger_ui/templates/index.html
RackioSwagger-0.7.dist-info/LICENSE
RackioSwagger-0.7.dist-info/METADATA
RackioSwagger-0.7.dist-info/WHEEL
RackioSwagger-0.7.dist-info/top_level.txt
RackioSwagger-0.7.dist-info/RECORD
