Metadata-Version: 2.1
Name: RackioSwagger
Version: 0.7
Summary: A Rackio extension to enable Swagger UI in API definitions
Home-page: https://github.com/rack-io/rackio-swagger
Author: Nelson Carrasquel
Author-email: rackio.framework@outlook.com
License: MIT
Platform: UNKNOWN
Classifier: Programming Language :: Python :: 3
Classifier: License :: OSI Approved :: MIT License
Classifier: Operating System :: OS Independent
Requires-Dist: falcon
Requires-Dist: Jinja2
Requires-Dist: deepmerge
